Metadata-Version: 1.0
Name: uis
Version: 0.0.5
Summary: uis
Home-page: UNKNOWN
Author: UNKNOWN
Author-email: v.zagumennikov@uiscom.ru
License: UNKNOWN
Platform: UNKNOWN
